{
  "$schema": "https://ui.shadcn.com/schema/registry-item.json",
  "name": "animate-in-stagger-demo",
  "type": "registry:block",
  "author": "patrick prunty <https://www.patrickprunty.com>",
  "registryDependencies": [
    "https://deltacomponents.dev/r/animate-in.json"
  ],
  "files": [
    {
      "path": "registry/examples/animate-in-stagger-demo.tsx",
      "content": "\"use client\"\n\nimport React from \"react\"\n\nimport AnimateIn from \"@/registry/animations/animate-in\"\n\nexport default function AnimateInStaggerDemo() {\n  return (\n    <div className=\"space-y-8 py-8\">\n      <AnimateIn direction=\"up\" duration={0.6}>\n        <h2 className=\"text-2xl font-bold text-center\">Staggered Animation</h2>\n        <p className=\"text-center text-muted-foreground mt-2\">\n          Each card animates in sequence with a small delay\n        </p>\n      </AnimateIn>\n\n      <AnimateIn direction=\"up\" staggerChildren={0.15} duration={0.5}>\n        <div className=\"grid md:grid-cols-3 gap-6\">\n          <div className=\"p-6 bg-gradient-to-br from-blue-50 to-blue-100 dark:from-blue-950/50 dark:to-blue-900/50 rounded-lg border\">\n            <div className=\"w-12 h-12 bg-blue-500 rounded-lg mb-4 flex items-center justify-center\">\n              <span className=\"text-white font-bold\">1</span>\n            </div>\n            <h3 className=\"font-semibold mb-2\">Feature One</h3>\n            <p className=\"text-sm text-muted-foreground\">\n              The first feature in our staggered animation sequence\n            </p>\n          </div>\n\n          <div className=\"p-6 bg-gradient-to-br from-green-50 to-green-100 dark:from-green-950/50 dark:to-green-900/50 rounded-lg border\">\n            <div className=\"w-12 h-12 bg-green-500 rounded-lg mb-4 flex items-center justify-center\">\n              <span className=\"text-white font-bold\">2</span>\n            </div>\n            <h3 className=\"font-semibold mb-2\">Feature Two</h3>\n            <p className=\"text-sm text-muted-foreground\">\n              The second feature appears with a slight delay\n            </p>\n          </div>\n\n          <div className=\"p-6 bg-gradient-to-br from-purple-50 to-purple-100 dark:from-purple-950/50 dark:to-purple-900/50 rounded-lg border\">\n            <div className=\"w-12 h-12 bg-purple-500 rounded-lg mb-4 flex items-center justify-center\">\n              <span className=\"text-white font-bold\">3</span>\n            </div>\n            <h3 className=\"font-semibold mb-2\">Feature Three</h3>\n            <p className=\"text-sm text-muted-foreground\">\n              The final feature completes the staggered sequence\n            </p>\n          </div>\n        </div>\n      </AnimateIn>\n\n      <AnimateIn\n        direction=\"up\"\n        staggerChildren={0.1}\n        duration={0.4}\n        delay={0.5}\n      >\n        <div className=\"flex flex-wrap gap-3 justify-center\">\n          <div className=\"px-4 py-2 bg-muted rounded-full\">Tag One</div>\n          <div className=\"px-4 py-2 bg-muted rounded-full\">Tag Two</div>\n          <div className=\"px-4 py-2 bg-muted rounded-full\">Tag Three</div>\n          <div className=\"px-4 py-2 bg-muted rounded-full\">Tag Four</div>\n          <div className=\"px-4 py-2 bg-muted rounded-full\">Tag Five</div>\n        </div>\n      </AnimateIn>\n    </div>\n  )\n}\n",
      "type": "registry:block",
      "target": "/components/delta/examples/animate-in-stagger-demo.tsx"
    }
  ]
}